aigo_pkg/__init__.py
aigo_pkg/aigofirst.py
aigofirst-0.0.1.dist-info/METADATA
aigofirst-0.0.1.dist-info/WHEEL
aigofirst-0.0.1.dist-info/top_level.txt
aigofirst-0.0.1.dist-info/RECORD
