Metadata-Version: 2.1
Name: aigofirst
Version: 0.0.1
Summary: 初始化
Home-page: https://git.geedos.com/algorithm/aigo
Author: lycra
Author-email: lycrali@careerintlinc.com
License: UNKNOWN
Platform: UNKNOWN
Requires-Python: >=3.6
